tanukia/client.py
tanukia/http.py
tanukia/model.py
tanukia-1.0.0.dist-info/METADATA
tanukia-1.0.0.dist-info/WHEEL
tanukia-1.0.0.dist-info/top_level.txt
tanukia-1.0.0.dist-info/RECORD
