Metadata-Version: 2.1
Name: tanukia
Version: 1.0.0
Summary: 히토미 검색 라이브러리
Home-page: https://github.com/VoidAsMad/tanukia
Author: VoidAsMad
Author-email: voidasmad@gmail.com
License: MIT
Platform: UNKNOWN
Requires-Python: >=3
